LICENSE
MANIFEST.in
README.rst
fujita.py
setup.py
django_fujita.egg-info/PKG-INFO
django_fujita.egg-info/SOURCES.txt
django_fujita.egg-info/dependency_links.txt
django_fujita.egg-info/requires.txt
django_fujita.egg-info/top_level.txt
fujita/__init__.py
fujita/handlers.py
fujita/main.py
fujita/runner.py
fujita/templates/index.html