Metadata-Version: 1.0
Name: django-fujita
Version: 0.3
Summary: A web based console for Django's development server built using Tornado
Home-page: https://github.com/fatbox/django-fujita
Author: Evan Borgstrom
Author-email: evan@fatbox.ca
License: Apache License, Version 2.0
Platform: UNKNOWN
Classifier: Development Status :: 3 - Alpha
Classifier: Framework :: Django
Classifier: Intended Audience :: Developers
Classifier: License :: OSI Approved :: Apache Software License
Classifier: Natural Language :: English
Classifier: Topic :: Software Development :: Libraries
Classifier: Topic :: Software Development :: Libraries :: Python Modules
